ttr/__init__.py
ttr/server.py
ttr/tstlib.py
ttr/tests/__init__.py
ttr/tests/test_integration.py
ttr/tests/test_server.py
ttr/tests/test_tstlib.py
ttr-0.1.1.data/scripts/ttr
ttr-0.1.1.data/scripts/ttr-start
ttr-0.1.1.dist-info/DESCRIPTION.rst
ttr-0.1.1.dist-info/METADATA
ttr-0.1.1.dist-info/RECORD
ttr-0.1.1.dist-info/WHEEL
ttr-0.1.1.dist-info/metadata.json
ttr-0.1.1.dist-info/top_level.txt
