Metadata-Version: 2.0
Name: ttr
Version: 0.1.1
Summary: Turbo test runner
Home-page: https://github.com/amadev/ttr
Author: Andrey Volkov
Author-email: amadev@mail.ru
License: MIT
Keywords: test runner
Platform: UNKNOWN
Classifier: Development Status :: 3 - Alpha
Classifier: Environment :: Console
Classifier: Intended Audience :: Developers
Classifier: Intended Audience :: System Administrators
Classifier: License :: OSI Approved :: MIT License
Classifier: Operating System :: POSIX :: Linux
Classifier: Programming Language :: Python :: 3
Classifier: Topic :: Utilities
Requires-Dist: inotify
Requires-Dist: mock
Requires-Dist: extras
Requires-Dist: testtools
